[{"name": "SDG_INDICATOR__GLOBAL", "field": {"label": "Indicator (global)", "translation_key": "metadata_fields.SDG_INDICATOR", "scope": "global", "element": "text"}}, {"name": "SDG_TARGET__GLOBAL", "field": {"label": "Target (global)", "translation_key": "metadata_fields.SDG_TARGET", "scope": "global", "element": "text"}}, {"name": "META_LAST_UPDATE__GLOBAL", "field": {"label": "Metadata update (global)", "translation_key": "metadata_fields.META_LAST_UPDATE", "scope": "global", "element": "text"}}, {"name": "SDG_CUSTODIAN_AGENCIES__GLOBAL", "field": {"label": "International organisations(s) responsible for global monitoring (global)", "translation_key": "metadata_fields.SDG_CUSTODIAN_AGENCIES", "scope": "global", "element": "text"}}, {"name": "SDG_RELATED_INDICATORS__GLOBAL", "field": {"label": "Related indicators (global)", "translation_key": "metadata_fields.SDG_RELATED_INDICATORS", "scope": "global", "element": "text"}}, {"name": "SDG_INDICATOR_INFO", "field": {"label": "Indicator information", "translation_key": "metadata_fields.SDG_INDICATOR_INFO", "scope": "national", "element": "text"}}, {"name": "SDG_GOAL", "field": {"label": "Goal", "translation_key": "metadata_fields.SDG_GOAL", "scope": "national", "element": "text"}}, {"name": "SDG_TARGET", "field": {"label": "Target", "translation_key": "metadata_fields.SDG_TARGET", "scope": "national", "element": "text"}}, {"name": "SDG_INDICATOR", "field": {"label": "Indicator", "translation_key": "metadata_fields.SDG_INDICATOR", "scope": "national", "element": "text"}}, {"name": "SDG_SERIES_DESCR", "field": {"label": "Series", "translation_key": "metadata_fields.SDG_SERIES_DESCR", "scope": "national", "element": "text"}}, {"name": "META_LAST_UPDATE", "field": {"label": "Metadata update", "translation_key": "metadata_fields.META_LAST_UPDATE", "scope": "national", "element": "text"}}, {"name": "SDG_RELATED_INDICATORS", "field": {"label": "Related indicators", "translation_key": "metadata_fields.SDG_RELATED_INDICATORS", "scope": "national", "element": "text"}}, {"name": "CONTACT", "field": {"label": "Data reporter", "translation_key": "metadata_fields.CONTACT", "scope": "national", "element": "text"}}, {"name": "CONTACT_ORGANISATION", "field": {"label": "Organisation", "translation_key": "metadata_fields.CONTACT_ORGANISATION", "scope": "national", "element": "text"}}, {"name": "CONTACT_NAME", "field": {"label": "Contact person(s)", "translation_key": "metadata_fields.CONTACT_NAME", "scope": "national", "element": "text"}}, {"name": "ORGANISATION_UNIT", "field": {"label": "Contact organisation unit", "translation_key": "metadata_fields.ORGANISATION_UNIT", "scope": "national", "element": "text"}}, {"name": "CONTACT_FUNCT", "field": {"label": "Contact person function", "translation_key": "metadata_fields.CONTACT_FUNCT", "scope": "national", "element": "text"}}, {"name": "CONTACT_PHONE", "field": {"label": "Contact phone", "translation_key": "metadata_fields.CONTACT_PHONE", "scope": "national", "element": "text"}}, {"name": "CONTACT_MAIL", "field": {"label": "Contact mail", "translation_key": "metadata_fields.CONTACT_MAIL", "scope": "national", "element": "text"}}, {"name": "CONTACT_EMAIL", "field": {"label": "Contact email", "translation_key": "metadata_fields.CONTACT_EMAIL", "scope": "national", "element": "text"}}, {"name": "IND_DEF_CON_CLASS", "field": {"label": "Definition, concepts, and classifications", "translation_key": "metadata_fields.IND_DEF_CON_CLASS", "scope": "national", "element": "text"}}, {"name": "STAT_CONC_DEF", "field": {"label": "Definition and concepts", "translation_key": "metadata_fields.STAT_CONC_DEF", "scope": "national", "element": "text"}}, {"name": "UNIT_MEASURE", "field": {"label": "Unit of measure", "translation_key": "metadata_fields.UNIT_MEASURE", "scope": "national", "element": "text"}}, {"name": "CLASS_SYSTEM", "field": {"label": "Classifications", "translation_key": "metadata_fields.CLASS_SYSTEM", "scope": "national", "element": "text"}}, {"name": "SRC_TYPE_COLL_METHOD", "field": {"label": "Data source type and collection method", "translation_key": "metadata_fields.SRC_TYPE_COLL_METHOD", "scope": "national", "element": "text"}}, {"name": "SOURCE_TYPE", "field": {"label": "Data sources", "translation_key": "metadata_fields.SOURCE_TYPE", "scope": "national", "element": "text"}}, {"name": "COLL_METHOD", "field": {"label": "Data collection method", "translation_key": "metadata_fields.COLL_METHOD", "scope": "national", "element": "text"}}, {"name": "FREQ_COLL", "field": {"label": "Data collection calendar", "translation_key": "metadata_fields.FREQ_COLL", "scope": "national", "element": "text"}}, {"name": "REL_CAL_POLICY", "field": {"label": "Data release calendar", "translation_key": "metadata_fields.REL_CAL_POLICY", "scope": "national", "element": "text"}}, {"name": "DATA_SOURCE", "field": {"label": "Data providers", "translation_key": "metadata_fields.DATA_SOURCE", "scope": "national", "element": "text"}}, {"name": "COMPILING_ORG", "field": {"label": "Data compilers", "translation_key": "metadata_fields.COMPILING_ORG", "scope": "national", "element": "text"}}, {"name": "INST_MANDATE", "field": {"label": "Institutional mandate", "translation_key": "metadata_fields.INST_MANDATE", "scope": "national", "element": "text"}}, {"name": "OTHER_METHOD", "field": {"label": "Other methodological considerations", "translation_key": "metadata_fields.OTHER_METHOD", "scope": "national", "element": "text"}}, {"name": "RATIONALE", "field": {"label": "Rationale", "translation_key": "metadata_fields.RATIONALE", "scope": "national", "element": "text"}}, {"name": "REC_USE_LIM", "field": {"label": "Comment and limitations", "translation_key": "metadata_fields.REC_USE_LIM", "scope": "national", "element": "text"}}, {"name": "DATA_COMP", "field": {"label": "Method of computation", "translation_key": "metadata_fields.DATA_COMP", "scope": "national", "element": "text"}}, {"name": "DATA_VALIDATION", "field": {"label": "Validation", "translation_key": "metadata_fields.DATA_VALIDATION", "scope": "national", "element": "text"}}, {"name": "DOC_METHOD", "field": {"label": "Methods and guidance available to countries for the compilation of the data at the national level", "translation_key": "metadata_fields.DOC_METHOD", "scope": "national", "element": "text"}}, {"name": "QUALITY_MGMNT", "field": {"label": "Quality management", "translation_key": "metadata_fields.QUALITY_MGMNT", "scope": "national", "element": "text"}}, {"name": "QUALITY_ASSURE", "field": {"label": "Quality assurance", "translation_key": "metadata_fields.QUALITY_ASSURE", "scope": "national", "element": "text"}}, {"name": "QUALITY_ASSMNT", "field": {"label": "Quality assessment", "translation_key": "metadata_fields.QUALITY_ASSMNT", "scope": "national", "element": "text"}}, {"name": "COVERAGE", "field": {"label": "Data availability and disaggregation", "translation_key": "metadata_fields.COVERAGE", "scope": "national", "element": "text"}}, {"name": "COMPARABILITY", "field": {"label": "Comparability/deviation from international standards", "translation_key": "metadata_fields.COMPARABILITY", "scope": "national", "element": "text"}}, {"name": "OTHER_DOC", "field": {"label": "References and Documentation", "translation_key": "metadata_fields.OTHER_DOC", "scope": "national", "element": "text"}}, {"name": "national_data_update_url", "field": {"label": "Data last updated", "translation_key": "metadata_fields.national_data_update_url", "scope": "national", "element": "text"}}, {"name": "national_data_update_url_text", "field": {"label": "Data last updated", "translation_key": "metadata_fields.national_data_update_url_text", "scope": "national", "element": "text"}}, {"name": "national_metadata_update_url", "field": {"label": "Metadata last updated", "translation_key": "metadata_fields.national_metadata_update_url", "scope": "national", "element": "text"}}, {"name": "national_metadata_update_url_text", "field": {"label": "Metadata last updated", "translation_key": "metadata_fields.national_metadata_update_url_text", "scope": "national", "element": "text"}}, {"name": "source_active_1", "field": {"help": "Whether or not to display this source", "label": "Source 1 active", "value": true, "translation_key": "metadata_fields.source_active_1", "element": "text"}}, {"name": "source_organisation_1", "field": {"label": "Organisation", "translation_key": "metadata_fields.source_organisation_1", "scope": "source_1", "element": "text"}}, {"name": "source_periodicity_1", "field": {"label": "Periodicity", "translation_key": "metadata_fields.source_periodicity_1", "scope": "source_1", "element": "text"}}, {"name": "source_earliest_available_1", "field": {"label": "Earliest available data", "translation_key": "metadata_fields.source_earliest_available_1", "scope": "source_1", "element": "text"}}, {"name": "source_geographical_coverage_1", "field": {"label": "Geographical coverage", "translation_key": "metadata_fields.source_geographical_coverage_1", "scope": "source_1", "element": "text"}}, {"name": "source_url_1", "field": {"label": "Link to data source", "translation_key": "metadata_fields.source_url_1", "scope": "source_1", "element": "text"}}, {"name": "source_url_text_1", "field": {"label": "Link to data source text", "value": "Link to source", "translation_key": "metadata_fields.source_url_text_1", "scope": "source_1", "element": "text"}}, {"name": "source_release_date_1", "field": {"help": "A date in YYYY-MM-DD format", "label": "Release date", "translation_key": "metadata_fields.source_release_date_1", "scope": "source_1", "element": "text"}}, {"name": "source_next_release_1", "field": {"help": "A date in YYYY-MM-DD format", "label": "Next release", "translation_key": "metadata_fields.source_next_release_1", "scope": "source_1", "element": "text"}}, {"name": "source_statistical_classification_1", "field": {"label": "Statistical classification", "translation_key": "metadata_fields.source_statistical_classification_1", "scope": "source_1", "element": "text"}}, {"name": "source_contact_1", "field": {"label": "Contact details", "translation_key": "metadata_fields.source_contact_1", "scope": "source_1", "element": "text"}}, {"name": "source_other_info_1", "field": {"label": "Other information", "translation_key": "metadata_fields.source_other_info_1", "scope": "source_1", "element": "text"}}, {"name": "source_active_2", "field": {"help": "Whether or not to display this source", "label": "Source 2 active", "value": false, "translation_key": "metadata_fields.source_active_1", "element": "text"}}, {"name": "source_organisation_2", "field": {"label": "Organisation", "translation_key": "metadata_fields.source_organisation_1", "scope": "source_2", "element": "text"}}, {"name": "source_periodicity_2", "field": {"label": "Periodicity", "translation_key": "metadata_fields.source_periodicity_1", "scope": "source_2", "element": "text"}}, {"name": "source_earliest_available_2", "field": {"label": "Earliest available data", "translation_key": "metadata_fields.source_earliest_available_1", "scope": "source_2", "element": "text"}}, {"name": "source_geographical_coverage_2", "field": {"label": "Geographical coverage", "translation_key": "metadata_fields.source_geographical_coverage_1", "scope": "source_2", "element": "text"}}, {"name": "source_url_2", "field": {"label": "Link to data source", "translation_key": "metadata_fields.source_url_1", "scope": "source_2", "element": "text"}}, {"name": "source_url_text_2", "field": {"label": "Link to data source text", "value": "Link to Source", "translation_key": "metadata_fields.source_url_text_1", "scope": "source_2", "element": "text"}}, {"name": "source_release_date_2", "field": {"help": "A date in YYYY-MM-DD format", "label": "Release date", "translation_key": "metadata_fields.source_release_date_1", "scope": "source_2", "element": "text"}}, {"name": "source_next_release_2", "field": {"help": "A date in YYYY-MM-DD format", "label": "Next release", "translation_key": "metadata_fields.source_next_release_1", "scope": "source_2", "element": "text"}}, {"name": "source_statistical_classification_2", "field": {"label": "Statistical classification", "translation_key": "metadata_fields.source_statistical_classification_1", "scope": "source_2", "element": "text"}}, {"name": "source_contact_2", "field": {"label": "Contact details", "translation_key": "metadata_fields.source_contact_1", "scope": "source_2", "element": "text"}}, {"name": "source_other_info_2", "field": {"label": "Other information", "translation_key": "metadata_fields.source_other_info_1", "scope": "source_2", "element": "text"}}, {"name": "source_active_3", "field": {"help": "Whether or not to display this source", "label": "Source 3 active", "value": false, "translation_key": "metadata_fields.source_active_1", "element": "text"}}, {"name": "source_organisation_3", "field": {"label": "Organisation", "translation_key": "metadata_fields.source_organisation_1", "scope": "source_3", "element": "text"}}, {"name": "source_periodicity_3", "field": {"label": "Periodicity", "translation_key": "metadata_fields.source_periodicity_1", "scope": "source_3", "element": "text"}}, {"name": "source_earliest_available_3", "field": {"label": "Earliest available data", "translation_key": "metadata_fields.source_earliest_available_1", "scope": "source_3", "element": "text"}}, {"name": "source_geographical_coverage_3", "field": {"label": "Geographical coverage", "translation_key": "metadata_fields.source_geographical_coverage_1", "scope": "source_3", "element": "text"}}, {"name": "source_url_3", "field": {"label": "Link to data source", "value": "Link to source", "translation_key": "metadata_fields.source_url_1", "scope": "source_3", "element": "text"}}, {"name": "source_url_text_3", "field": {"label": "Link to data source text", "translation_key": "metadata_fields.source_url_text_1", "scope": "source_3", "element": "text"}}, {"name": "source_release_date_3", "field": {"help": "A date in YYYY-MM-DD format", "label": "Release date", "translation_key": "metadata_fields.source_release_date_1", "scope": "source_3", "element": "text"}}, {"name": "source_next_release_3", "field": {"help": "A date in YYYY-MM-DD format", "label": "Next release", "translation_key": "metadata_fields.source_next_release_1", "scope": "source_3", "element": "text"}}, {"name": "source_statistical_classification_3", "field": {"label": "Statistical classification", "translation_key": "metadata_fields.source_statistical_classification_1", "scope": "source_3", "element": "text"}}, {"name": "source_contact_3", "field": {"label": "Contact details", "translation_key": "metadata_fields.source_contact_1", "scope": "source_3", "element": "text"}}, {"name": "source_other_info_3", "field": {"label": "Other information", "translation_key": "metadata_fields.source_other_info_1", "scope": "source_3", "element": "text"}}, {"name": "source_active_4", "field": {"help": "Whether or not to display this source", "label": "Source 4 active", "value": false, "translation_key": "metadata_fields.source_active_1", "element": "text"}}, {"name": "source_organisation_4", "field": {"label": "Organisation", "translation_key": "metadata_fields.source_organisation_1", "scope": "source_4", "element": "text"}}, {"name": "source_periodicity_4", "field": {"label": "Periodicity", "translation_key": "metadata_fields.source_periodicity_1", "scope": "source_4", "element": "text"}}, {"name": "source_earliest_available_4", "field": {"label": "Earliest available data", "translation_key": "metadata_fields.source_earliest_available_1", "scope": "source_4", "element": "text"}}, {"name": "source_geographical_coverage_4", "field": {"label": "Geographical coverage", "translation_key": "metadata_fields.source_geographical_coverage_1", "scope": "source_4", "element": "text"}}, {"name": "source_url_4", "field": {"label": "Link to data source", "translation_key": "metadata_fields.source_url_1", "scope": "source_4", "element": "text"}}, {"name": "source_url_text_4", "field": {"label": "Link to data source text", "value": "Link to source", "translation_key": "metadata_fields.source_url_text_1", "scope": "source_4", "element": "text"}}, {"name": "source_release_date_4", "field": {"help": "A date in YYYY-MM-DD format", "label": "Release date", "translation_key": "metadata_fields.source_release_date_1", "scope": "source_4", "element": "text"}}, {"name": "source_next_release_4", "field": {"help": "A date in YYYY-MM-DD format", "label": "Next release", "translation_key": "metadata_fields.source_next_release_1", "scope": "source_4", "element": "text"}}, {"name": "source_statistical_classification_4", "field": {"label": "Statistical classification", "translation_key": "metadata_fields.source_statistical_classification_1", "scope": "source_4", "element": "text"}}, {"name": "source_contact_4", "field": {"label": "Contact details", "translation_key": "metadata_fields.source_contact_1", "scope": "source_4", "element": "text"}}, {"name": "source_other_info_4", "field": {"label": "Other information", "translation_key": "metadata_fields.source_other_info_1", "scope": "source_4", "element": "text"}}, {"name": "source_active_5", "field": {"help": "Whether or not to display this source", "label": "Source 5 active", "value": false, "translation_key": "metadata_fields.source_active_1", "element": "text"}}, {"name": "source_organisation_5", "field": {"label": "Organisation", "translation_key": "metadata_fields.source_organisation_1", "scope": "source_5", "element": "text"}}, {"name": "source_periodicity_5", "field": {"label": "Periodicity", "translation_key": "metadata_fields.source_periodicity_1", "scope": "source_5", "element": "text"}}, {"name": "source_earliest_available_5", "field": {"label": "Earliest available data", "translation_key": "metadata_fields.source_earliest_available_1", "scope": "source_5", "element": "text"}}, {"name": "source_geographical_coverage_5", "field": {"label": "Geographical coverage", "translation_key": "metadata_fields.source_geographical_coverage_1", "scope": "source_5", "element": "text"}}, {"name": "source_url_5", "field": {"label": "Link to data source", "translation_key": "metadata_fields.source_url_1", "scope": "source_5", "element": "text"}}, {"name": "source_url_text_5", "field": {"label": "Link to data source text", "value": "Link to source", "translation_key": "metadata_fields.source_url_text_1", "scope": "source_5", "element": "text"}}, {"name": "source_release_date_5", "field": {"help": "A date in YYYY-MM-DD format", "label": "Release date", "translation_key": "metadata_fields.source_release_date_1", "scope": "source_5", "element": "text"}}, {"name": "source_next_release_5", "field": {"help": "A date in YYYY-MM-DD format", "label": "Next release", "translation_key": "metadata_fields.source_next_release_1", "scope": "source_5", "element": "text"}}, {"name": "source_statistical_classification_5", "field": {"label": "Statistical classification", "translation_key": "metadata_fields.source_statistical_classification_1", "scope": "source_5", "element": "text"}}, {"name": "source_contact_5", "field": {"label": "Contact details", "translation_key": "metadata_fields.source_contact_1", "scope": "source_5", "element": "text"}}, {"name": "source_other_info_5", "field": {"label": "Other information", "translation_key": "metadata_fields.source_other_info_1", "scope": "source_5", "element": "text"}}, {"name": "source_active_6", "field": {"help": "Whether or not to display this source", "label": "Source 6 active", "value": false, "translation_key": "metadata_fields.source_active_1", "element": "text"}}, {"name": "source_organisation_6", "field": {"label": "Organisation", "translation_key": "metadata_fields.source_organisation_1", "scope": "source_6", "element": "text"}}, {"name": "source_periodicity_6", "field": {"label": "Periodicity", "translation_key": "metadata_fields.source_periodicity_1", "scope": "source_6", "element": "text"}}, {"name": "source_earliest_available_6", "field": {"label": "Earliest available data", "translation_key": "metadata_fields.source_earliest_available_1", "scope": "source_6", "element": "text"}}, {"name": "source_geographical_coverage_6", "field": {"label": "Geographical coverage", "translation_key": "metadata_fields.source_geographical_coverage_1", "scope": "source_6", "element": "text"}}, {"name": "source_url_6", "field": {"label": "Link to data source", "translation_key": "metadata_fields.source_url_1", "scope": "source_6", "element": "text"}}, {"name": "source_url_text_6", "field": {"label": "Link to data source text", "value": "Link to source", "translation_key": "metadata_fields.source_url_text_1", "scope": "source_6", "element": "text"}}, {"name": "source_release_date_6", "field": {"help": "A date in YYYY-MM-DD format", "label": "Release date", "translation_key": "metadata_fields.source_release_date_1", "scope": "source_6", "element": "text"}}, {"name": "source_next_release_6", "field": {"help": "A date in YYYY-MM-DD format", "label": "Next release", "translation_key": "metadata_fields.source_next_release_1", "scope": "source_6", "element": "text"}}, {"name": "source_statistical_classification_6", "field": {"label": "Statistical classification", "translation_key": "metadata_fields.source_statistical_classification_1", "scope": "source_6", "element": "text"}}, {"name": "source_contact_6", "field": {"label": "Contact details", "translation_key": "metadata_fields.source_contact_1", "scope": "source_6", "element": "text"}}, {"name": "source_other_info_6", "field": {"label": "Other information", "translation_key": "metadata_fields.source_other_info_1", "scope": "source_6", "element": "text"}}, {"name": "un_designated_tier", "field": {"label": "UN designated tier", "translation_key": "metadata_fields.un_designated_tier", "scope": "global", "element": "text"}}]